termx/__init__.py
termx/termx.py
termx-0.1.1.dist-info/METADATA
termx-0.1.1.dist-info/WHEEL
termx-0.1.1.dist-info/top_level.txt
termx-0.1.1.dist-info/RECORD
