Metadata-Version: 2.1
Name: termx
Version: 0.1.1
Summary: Create terminal applications with ease.
Home-page: https://github.com/Izaan17/termx
Author: Izaan Noman
Author-email: 
License: MIT
Platform: UNKNOWN
Requires-Dist: colorama
Requires-Dist: bs4
